[{"items":[{"quantity":3,"id":6637151715491,"title":"Vision","description":"When I say the word 'beauty', what do you envision? ⁠This magnificent abstract painting feels new everytime you look at it.⁠ With loads of different colors, long brushstrokes and subtle details, this painting never gets boring!⁠","price":"359.00","compare_at_price":"720.00","image":{"width":790,"height":730,"src":"https://cdn.shopify.com/s/files/1/0557/2280/3363/products/Bildschirmfoto2022-03-29um21.53.15.png?v=1648583612"}},{"quantity":5,"id":6637152043171,"title":"Flower","description":"Designed to resonate & spark a mix of feelings. Every day. Whether you love art or just looking to decorate, this handmade painting will instantly create a new ambience in your home or office.","price":"251.00","compare_at_price":"503.00","image":{"width":800,"height":800,"src":"https://cdn.shopify.com/s/files/1/0557/2280/3363/products/20200816212113.jpg?v=1618657124"}},{"quantity":3,"id":6716240691363,"title":"Rainy","description":"Designed to resonate & spark a mix of feelings. Every day. Whether you love art or just looking to decorate, this handmade painting will instantly create a new ambience in your home or office.","price":"293.00","compare_at_price":"586.00","image":{"width":3000,"height":3000,"src":"https://cdn.shopify.com/s/files/1/0557/2280/3363/products/053c.jpg?v=1647986532"}}],"customer":{"name":"Kartar ","email":"kartar@gmail.com","street":"Phase 7","postal-code":"140408","city":"Mohali","save-address":"on"},"id":"786.2355834062469"},{"items":[{"quantity":1,"id":6637151715491,"title":"Vision","description":"When I say the word 'beauty', what do you envision? ⁠This magnificent abstract painting feels new everytime you look at it.⁠ With loads of different colors, long brushstrokes and subtle details, this painting never gets boring!⁠","price":"359.00","compare_at_price":"720.00","image":{"width":790,"height":730,"src":"https://cdn.shopify.com/s/files/1/0557/2280/3363/products/Bildschirmfoto2022-03-29um21.53.15.png?v=1648583612"}},{"quantity":1,"id":6637152043171,"title":"Flower","description":"Designed to resonate & spark a mix of feelings. Every day. Whether you love art or just looking to decorate, this handmade painting will instantly create a new ambience in your home or office.","price":"251.00","compare_at_price":"503.00","image":{"width":800,"height":800,"src":"https://cdn.shopify.com/s/files/1/0557/2280/3363/products/20200816212113.jpg?v=1618657124"}}],"customer":{"name":"Kartar ","email":"kartar@gmail.com","street":"Phase 7","postal-code":"140408","city":"Mohali","use-address":"on"},"id":"470.77080124411674"},{"items":[{"quantity":1,"id":6759993475235,"title":"Autumn","description":"Designed to resonate & spark a mix of feelings. Every day. Whether you love art or just looking to decorate, this handmade painting will instantly create a new ambience in your home or office.","price":"251.00","compare_at_price":"503.00","image":{"width":651,"height":628,"src":"https://cdn.shopify.com/s/files/1/0557/2280/3363/products/Bildschirmfoto2022-03-29um13.55.01.png?v=1648554935"}},{"quantity":1,"id":6716240691363,"title":"Rainy","description":"Designed to resonate & spark a mix of feelings. Every day. Whether you love art or just looking to decorate, this handmade painting will instantly create a new ambience in your home or office.","price":"293.00","compare_at_price":"586.00","image":{"width":3000,"height":3000,"src":"https://cdn.shopify.com/s/files/1/0557/2280/3363/products/053c.jpg?v=1647986532"}}],"customer":{"name":"John Doe","email":"johndoe123@gmail.com","street":"Wall Street","postal-code":"10005","city":"New York"},"id":"734.103214174015"}]